data_validation_framework/__init__.py
data_validation_framework/report.py
data_validation_framework/result.py
data_validation_framework/rst_tools.py
data_validation_framework/target.py
data_validation_framework/task.py
data_validation_framework/util.py
data_validation_framework-0.9.0.dist-info/AUTHORS.md
data_validation_framework-0.9.0.dist-info/LICENSE.txt
data_validation_framework-0.9.0.dist-info/METADATA
data_validation_framework-0.9.0.dist-info/WHEEL
data_validation_framework-0.9.0.dist-info/top_level.txt
data_validation_framework-0.9.0.dist-info/RECORD
