Metadata-Version: 2.1
Name: data-validation-framework
Version: 0.9.0
Summary: Simple framework to create data validation workflows.
Home-page: https://data-validation-framework.readthedocs.io
Author: Blue Brain Project, EPFL
License: Apache License 2.0
Project-URL: Tracker, https://github.com/BlueBrain/data-validation-framework/issues
Project-URL: Source, https://github.com/BlueBrain/data-validation-framework
Classifier: Development Status :: 4 - Beta
Classifier: Intended Audience :: Developers
Classifier: Intended Audience :: Science/Research
Classifier: License :: OSI Approved :: Apache Software License
Classifier: Programming Language :: Python
Classifier: Programming Language :: Python :: 3
Classifier: Programming Language :: Python :: 3.9
Classifier: Programming Language :: Python :: 3.10
Classifier: Programming Language :: Python :: 3.11
Classifier: Programming Language :: Python :: 3.12
Classifier: Topic :: Software Development :: Libraries :: Application Frameworks
Classifier: Topic :: Software Development :: Libraries :: Python Modules
Requires-Python: >=3.9
License-File: LICENSE.txt
License-File: AUTHORS.md
Requires-Dist: luigi >=3.1
Requires-Dist: luigi-tools >=0.0.18
Requires-Dist: numpy >=1.21
Requires-Dist: pandas >=1.3
Requires-Dist: rst2pdf >=0.99
Requires-Dist: sphinx >=7.4
Requires-Dist: tqdm >=4.40
Provides-Extra: docs
Requires-Dist: docutils <0.21 ; extra == 'docs'
Requires-Dist: m2r2 ; extra == 'docs'
Requires-Dist: sphinx ; extra == 'docs'
Requires-Dist: sphinx-bluebrain-theme ; extra == 'docs'
Provides-Extra: test
Requires-Dist: diff-pdf-visually >=1.6.2 ; extra == 'test'
Requires-Dist: pause >=0.2 ; extra == 'test'
Requires-Dist: pytest >=7 ; extra == 'test'
Requires-Dist: pytest-cov >=4.1 ; extra == 'test'
Requires-Dist: pytest-html >=3.2 ; extra == 'test'
